{
  "description": "A touch-optimized E-H/ExH viewer",
  "button": {
    "apply": "Apply",
    "clearHistory": "Clear All History",
    "close": "Close",
    "confirm": "Confirm",
    "default": "Default",
    "removeHistory": "Delete History"
  },
  "help": {
    "title": "Help",
    "content": {
      "Reader": [
        "**Tap** the center to show or hide the toolbar.",
        "**Swipe or scroll** in the reading direction; tap either side or use the **Arrow keys** to turn pages.",
        "**Pinch** to zoom the image. Or **double-tap** to enter zoom mode and use the **mouse wheel** to adjust the scale."
      ],
      "Browse": [
        "When **Enhance > Search Grids** is enabled, **swipe** horizontally to change search result pages."
      ],
      "Gallery": [
        "When **Enhance > Thumbs Grids** is enabled, **swipe** horizontally to change preview pages.",
        "The Page Bar in Gallery can be **dragged** to adjust the range."
      ]
    }
  },
  "reader": {
    "readingOptions": "Reading options",
    "adjustScrollViewport": "Adjust Scroll viewport size",
    "resizeScrollViewport": "Resize Scroll viewport",
    "fit": "Fit",
    "applyGlobally": "Set Default",
    "pagedMode": "Paged mode",
    "singlePageMode": "Single-page layout",
    "doublePageMode": "Double-page layout",
    "scrollMode": "Scroll mode",
    "rightTapPrevious": "Right side action:\nPrevious page",
    "rightTapNext": "Right side action:\nNext page",
    "directionRtl": "Reading direction:\n Right to left",
    "directionLtr": "Reading direction:\n Left to right",
    "directionTtb": "Reading direction:\n Top to bottom",
    "download": "Download",
    "downloadDisplayedImage": "Displayed image",
    "downloadOriginalImage": "Original image",
    "originalImageSource": "Original source provided by E-Hentai",
    "originalImageUnavailable": "Original image unavailable",
    "startReading": "Read",
    "continueReading": "Continue",
    "loading": "Loading...",
    "pages": "Pages",
    "endPage": "End",
    "end": "End of gallery. Tap to exit.",
    "failedPrefix": "Failed",
    "reloadPage": "Reload page"
  },
  "favorites": {
    "all": "All"
  },
  "history": {
    "clearConfirm": "Clear all reading history?",
    "empty": "No reading history",
    "limit": "(max {limit})",
    "visitedLabel": "[VISITED]",
    "range": "{start}-{end} in {total} histories",
    "readingLabel": "[READING]",
    "removeConfirm": "Remove this gallery from Read History?",
    "unread": "Unread"
  },
  "gallery": {
    "favoriteTag": "Add My Tag",
    "removeFavoriteTag": "Remove My Tag",
    "tagCollection": "Collection",
    "tagBehavior": "Behavior",
    "markTag": "Mark",
    "watchTag": "Watch",
    "hideTag": "Hide"
  },
  "settings": {
    "openSettings": "Settings",
    "menuLabel": "Ehpeek",
    "on": "On",
    "off": "Off",
    "discardChanges": "Discard unsaved settings changes?",
    "general": "General",
    "options": "Options",
    "about": "About",
    "readerLabel": "Reader",
    "readerHelp": "Opens gallery images in Ehpeek's reader",
    "readerFullscreenLabel": "Reader in Fullscreen",
    "readerFullscreenHelp": "Enters fullscreen when the Reader opens",
    "readerOptions": "Options",
    "openGalleryInNewTabLabel": "Gallery in New Tab",
    "openGalleryInNewTabHelp": "Opens Gallery links in a new browser tab",
    "enhance": "Enhance",
    "enhanceSearchLabel": "Search Grids",
    "enhanceSearchHelp": "Adds swipe navigation to search pages",
    "enhanceThumbsLabel": "Thumbs Grids",
    "enhanceThumbsHelp": "Adds swipe navigation and scrollable pages bar for gallery preview",
    "myTagsLabel": "My Tag in Gallery",
    "myTagsHelp": "Highlights your saved tags with colors in gallery",
    "historyLabel": "History",
    "readHistoryLabel": "Read History",
    "readHistoryHelp": "Remembers reading progress",
    "includeUnreadHistoryLabel": "Include Unread History",
    "includeUnreadHistoryHelp": "Adds opened galleries to Read History before reading starts",
    "searchHistoryLabel": "Search History",
    "searchHistoryHelp": "Remembers previous searches",
    "touchUiLabel": "Touch UI",
    "touchUiHelp": "Uses touch-friendly navigation UI."
  },
  "search": {
    "advancedOptions": "Advanced Options",
    "categories": "Categories",
    "fileSearch": "File Search"
  },
  "errors": {
    "imageNotFound": "Image not found",
    "downloadFailed": "Download failed",
    "loadFailed": "Load failed",
    "imageLoadFailed": "Image load failed",
    "previewPageSizeUnknown": "Cannot determine gallery preview page size",
    "searchPageContentNotFound": "Cannot find search page content"
  }
}
